calaccess_processed/__init__.py
calaccess_processed/apps.py
calaccess_processed/fields.py
calaccess_processed/managers.py
calaccess_processed/models.py
calaccess_processed/postgres.py
calaccess_processed/proxies.py
calaccess_processed/fixtures/divisions.json
calaccess_processed/fixtures/form460filing.json
calaccess_processed/fixtures/form460filingversion.json
calaccess_processed/management/__init__.py
calaccess_processed/management/commands/__init__.py
calaccess_processed/management/commands/_archivecalaccessprocessedfile.py
calaccess_processed/management/commands/processcalaccessdata.py
calaccess_processed/management/commands/verifycalaccessprocesseddata.py
calaccess_processed/migrations/0001_squashed_0014_rawfilertofilertypecdproxy_scrapedcandidateelectionproxy_scrapedcandidateproxy_scrapedincumbentelect.py
calaccess_processed/migrations/0014_pgcrypto.py
calaccess_processed/migrations/0015_auto_20180416_2200.py
calaccess_processed/migrations/0016_auto_20210619_1139.py
calaccess_processed/migrations/0017_remove_processeddataversion_raw_version_and_more.py
calaccess_processed/migrations/__init__.py
calaccess_processed/tests/__init__.py
calaccess_processed/tests/test_base_commands.py
calaccess_processed/tests/test_elections.py
calaccess_processed/tests/test_filing_models.py
calaccess_processed/tests/test_models.py
calaccess_processed/tests/test_processing.py
calaccess_processed_campaignfinance/__init__.py
calaccess_processed_campaignfinance/apps.py
calaccess_processed_campaignfinance/management/__init__.py
calaccess_processed_campaignfinance/management/commands/__init__.py
calaccess_processed_campaignfinance/management/commands/loadocdfilingsfrom460s.py
calaccess_processed_campaignfinance/managers/__init__.py
calaccess_processed_campaignfinance/managers/base.py
calaccess_processed_campaignfinance/managers/committees.py
calaccess_processed_campaignfinance/managers/filings.py
calaccess_processed_campaignfinance/managers/transactions.py
django_calaccess_processed_data-1.0.15.dist-info/licenses/LICENSE
django_calaccess_processed_data-1.0.15.dist-info/METADATA
django_calaccess_processed_data-1.0.15.dist-info/WHEEL
django_calaccess_processed_data-1.0.15.dist-info/top_level.txt
django_calaccess_processed_data-1.0.15.dist-info/RECORD
